{
    "2019":{
        "1": {
            "9": {
                "line": [
                    {
                        "color": "0",
                        "content": "研發部會議"
                    }
                ],
                "dot": []
            },
            "11": {
                "line": [
                    {
                        "color": "0",
                        "content": "公司尾牙"
                    }
                ],
                "dot": []
            },
            "16": {
                "line": [
                    {
                        "color": "0",
                        "content": "研發部會議"
                    }
                ],
                "dot": []
            },
            "18": {
                "line": [
                    {
                        "color": "0",
                        "content": "藥物專題演講"
                    }
                ],
                "dot": []
            },
            "23": {
                "line": [
                    {
                        "color": "0",
                        "content": "研發部會議"
                    }
                ],
                "dot": []
            },
            "30": {
                "line": [
                    {
                        "color": "0",
                        "content": "研發部會議"
                    }
                ],
                "dot": []
            }
        },
        "2":{
            "7": {
                "line": [
                    {
                        "color": "0",
                        "content": "到監獄找醫生"
                    }
                ],
                "dot": []
            },
            "8": {
                "line": [
                    {
                        "color": "0",
                        "content": "遊樂園玩"
                    }
                ],
                "dot": []
            },
            "13": {
                "line": [
                    {
                        "color": "0",
                        "content": "研發部會議"
                    }
                ],
                "dot": []
            },
            "20": {
                "line": [
                    {
                        "color": "0",
                        "content": "研發部會議"
                    }
                ],
                "dot": []
            },
            "22": {
                "line": [
                    {
                        "color": "0",
                        "content": "藥物專題演講"
                    }
                ],
                "dot": []
            },
            "27": {
                "line": [
                    {
                        "color": "0",
                        "content": "研發部會議"
                    }
                ],
                "dot": []
            }
        },
        "3":{
            "6": {
                "line": [
                    {
                        "color": "0",
                        "content": "研發部會議"
                    }
                ],
                "dot": []
            },
            "13": {
                "line": [
                    {
                        "color": "0",
                        "content": "研發部會議"
                    }
                ],
                "dot": []
            },
            "20": {
                "line": [
                    {
                        "color": "0",
                        "content": "研發部會議"
                    }
                ],
                "dot": []
            },
            "22": {
                "line": [
                    {
                        "color": "0",
                        "content": "藥物專題演講"
                    }
                ],
                "dot": []
            },
            "27": {
                "line": [
                    {
                        "color": "0",
                        "content": "研發部會議"
                    }
                ],
                "dot": []
            }
        },
        "4":{
            "3": {
                "line": [
                    {
                        "color": "0",
                        "content": "研發部會議"
                    }
                ],
                "dot": []
            },
            "7": {
                "line": [
                    {
                        "color": "0",
                        "content": "到監獄找醫生"
                    }
                ],
                "dot": []
            },
            "10": {
                "line": [
                    {
                        "color": "0",
                        "content": "研發部會議"
                    }
                ],
                "dot": []
            },
            "17": {
                "line": [
                    {
                        "color": "0",
                        "content": "研發部會議"
                    }
                ],
                "dot": []
            },
            "18": {
                "line": [
                    {
                        "color": "0",
                        "content": "羅璟宸生日"
                    }
                ],
                "dot": []
            },
            "19": {
                "line": [
                    {
                        "color": "0",
                        "content": "藥物專題演講"
                    }
                ],
                "dot": []
            },
            "24": {
                "line": [
                    {
                        "color": "0",
                        "content": "研發部會議"
                    }
                ],
                "dot": []
            }
        },
        "5":{
            "1": {
                "line": [
                    {
                        "color": "0",
                        "content": "研發部會議"
                    }
                ],
                "dot": []
            },
            "8": {
                "line": [
                    {
                        "color": "0",
                        "content": "研發部會議"
                    }
                ],
                "dot": []
            },
            "15": {
                "line": [
                    {
                        "color": "0",
                        "content": "研發部會議"
                    }
                ],
                "dot": []
            },
            "17": {
                "line": [
                    {
                        "color": "0",
                        "content": "藥物專題演講"
                    }
                ],
                "dot": []
            },
            "22": {
                "line": [
                    {
                        "color": "0",
                        "content": "研發部會議"
                    }
                ],
                "dot": []
            },
            "29": {
                "line": [
                    {
                        "color": "0",
                        "content": "研發部會議"
                    }
                ],
                "dot": []
            }
        },
        "6":{
            "5": {
                "line": [
                    {
                        "color": "0",
                        "content": "研發部會議"
                    }
                ],
                "dot": []
            },
            "7": {
                "line": [
                    {
                        "color": "0",
                        "content": "到監獄找醫生"
                    }
                ],
                "dot": []
            },
            "12": {
                "line": [
                    {
                        "color": "0",
                        "content": "研發部會議"
                    }
                ],
                "dot": []
            },
            "19": {
                "line": [
                    {
                        "color": "0",
                        "content": "研發部會議"
                    }
                ],
                "dot": []
            },
            "26": {
                "line": [
                    {
                        "color": "0",
                        "content": "研發部會議"
                    }
                ],
                "dot": []
            }
        },
        "7":{
            "3": {
                "line": [
                    {
                        "color": "0",
                        "content": "研發部會議"
                    }
                ],
                "dot": []
            },
            "10": {
                "line": [
                    {
                        "color": "0",
                        "content": "研發部會議"
                    }
                ],
                "dot": []
            },
            "14": {
                "line": [
                    {
                        "color": "1",
                        "content": "交往第一天"
                    }
                ],
                "dot": []
            },
            "17": {
                "line": [
                    {
                        "color": "0",
                        "content": "研發部會議"
                    }
                ],
                "dot": []
            },
            "19": {
                "line": [
                    {
                        "color": "0",
                        "content": "藥物專題演講"
                    }
                ],
                "dot": []
            },
            "24": {
                "line": [
                    {
                        "color": "0",
                        "content": "研發部會議"
                    }
                ],
                "dot": []
            },
            "31": {
                "line": [
                    {
                        "color": "0",
                        "content": "研發部會議"
                    }
                ],
                "dot": []
            }
        },
        "8":{
            "7": {
                "line": [
                    {
                        "color": "0",
                        "content": "到監獄找醫生"
                    }
                ],
                "dot": []
            },
            "8": {
                "line": [
                    {
                        "color": "0",
                        "content": "回去爸爸公司"
                    }
                ],
                "dot": []
            },
            "14": {
                "line": [
                    {
                        "color": "0",
                        "content": "研發部會議"
                    }
                ],
                "dot": []
            },
            "16": {
                "line": [
                    {
                        "color": "0",
                        "content": "藥物專題演講"
                    }
                ],
                "dot": []
            },
            "21": {
                "line": [
                    {
                        "color": "0",
                        "content": "研發部會議"
                    }
                ],
                "dot": []
            },
            "24": {
                "line": [
                    {
                        "color": "1",
                        "content": "我的生日"
                    }
                ],
                "dot": []
            },
            "28": {
                "line": [
                    {
                        "color": "0",
                        "content": "研發部會議"
                    }
                ],
                "dot": []
            }
        },
        "9":{
            "4": {
                "line": [
                    {
                        "color": "0",
                        "content": "研發部會議"
                    }
                ],
                "dot": []
            },
            "11": {
                "line": [
                    {
                        "color": "0",
                        "content": "研發部會議"
                    }
                ],
                "dot": []
            },
            "18": {
                "line": [
                    {
                        "color": "0",
                        "content": "研發部會議"
                    }
                ],
                "dot": []
            },
            "20": {
                "line": [
                    {
                        "color": "0",
                        "content": "藥物專題演講"
                    }
                ],
                "dot": []
            },
            "25": {
                "line": [
                    {
                        "color": "0",
                        "content": "研發部會議"
                    }
                ],
                "dot": []
            }
        },
        "10":{
            "2": {
                "line": [
                    {
                        "color": "0",
                        "content": "研發部會議"
                    }
                ],
                "dot": []
            },
            "7": {
                "line": [
                    {
                        "color": "0",
                        "content": "到監獄找醫生"
                    }
                ],
                "dot": []
            },
            "9": {
                "line": [
                    {
                        "color": "0",
                        "content": "研發部會議"
                    }
                ],
                "dot": []
            },
            "16": {
                "line": [
                    {
                        "color": "0",
                        "content": "研發部會議"
                    }
                ],
                "dot": []
            },
            "18": {
                "line": [
                    {
                        "color": "0",
                        "content": "藥物專題演講"
                    }
                ],
                "dot": []
            },
            "23": {
                "line": [
                    {
                        "color": "0",
                        "content": "研發部會議"
                    }
                ],
                "dot": []
            },
            "30": {
                "line": [
                    {
                        "color": "0",
                        "content": "研發部會議"
                    }
                ],
                "dot": []
            }
        },
        "11":{
            "6": {
                "line": [
                    {
                        "color": "0",
                        "content": "研發部會議"
                    }
                ],
                "dot": []
            },
            "13": {
                "line": [
                    {
                        "color": "0",
                        "content": "研發部會議"
                    }
                ],
                "dot": []
            },
            "20": {
                "line": [
                    {
                        "color": "0",
                        "content": "研發部會議"
                    }
                ],
                "dot": []
            },
            "22": {
                "line": [
                    {
                        "color": "0",
                        "content": "藥物專題演講"
                    }
                ],
                "dot": []
            },
            "27": {
                "line": [
                    {
                        "color": "0",
                        "content": "研發部會議"
                    }
                ],
                "dot": []
            }
        },
        "12":{
            "4": {
                "line": [
                    {
                        "color": "0",
                        "content": "研發部會議"
                    }
                ],
                "dot": []
            },
            "7": {
                "line": [
                    {
                        "color": "0",
                        "content": "到監獄看醫生"
                    }
                ],
                "dot": []
            },
            "11": {
                "line": [
                    {
                        "color": "0",
                        "content": "研發部會議"
                    }
                ],
                "dot": []
            },
            "18": {
                "line": [
                    {
                        "color": "0",
                        "content": "研發部會議"
                    }
                ],
                "dot": []
            },
            "20": {
                "line": [
                    {
                        "color": "0",
                        "content": "藥物專題演講"
                    }
                ],
                "dot": []
            },
            "25": {
                "line": [
                    {
                        "color": "0",
                        "content": "研發部會議"
                    },{
                        "color": "1",
                        "content": "聖誕節交換禮物"
                    }

                ],
                "dot": []
            },
            "26": {
                "line": [
                    {
                        "color": "0",
                        "content": "爸爸忌日"
                    }
                ],
                "dot": []
            }
        }

    },
    "2020": {
        "1": {
            "8": {
                "line": [
                    {
                        "color": "0",
                        "content": "研發部會議（年度計畫）"
                    }
                ],
                "dot": []
            },
            "15": {
                "line": [{
                    "color": "0",
                    "content": "研發部會議"
                }],
                "dot": []
            },
            "17": {
                "line": [{
                    "color": "0",
                    "content": "藥物專題演講"
                }],
                "dot": []
            },
            "22": {
                "line": [{
                    "color": "0",
                    "content": "研發部會議"
                }],
                "dot": []
            }
        },
        "2":{
            "5":{
                "line": [{
                    "color": "0",
                    "content": "研發部會議"
                }],
                "dot": []
            },
            "7":{
                "line": [{
                    "color": "0",
                    "content": "到監獄找醫生"
                }],
                "dot": []
            },
            "12":{
                "line": [{
                    "color": "0",
                    "content": "研發部會議"
                }],
                "dot": []
            },
            "19":{
                "line": [{
                    "color": "0",
                    "content": "研發部會議"
                }],
                "dot": []
            },
            "21":{
                "line": [{
                    "color": "0",
                    "content": "藥物專題演講"
                }],
                "dot": []
            },
            "26":{
                "line": [{
                    "color": "0",
                    "content": "研發部會議"
                }],
                "dot": []
            }
        },
        "3":{
            "4":{
                "line": [{
                    "color": "0",
                    "content": "研發部會議"
                }],
                "dot": []
            },
            "11":{
                "line": [{
                    "color": "0",
                    "content": "研發部會議"
                }],
                "dot": []
            },
            "18":{
                "line": [{
                    "color": "0",
                    "content": "研發部會議"
                }],
                "dot": []
            },
            "20":{
                "line": [{
                    "color": "0",
                    "content": "藥物專題演講"
                }],
                "dot": []
            },
            "25":{
                "line": [{
                    "color": "0",
                    "content": "研發部會議"
                }],
                "dot": []
            }
        },
        "4":{
            "1":{
                "line": [{
                    "color": "0",
                    "content": "研發部會議"
                }],
                "dot": []
            },
            "7":{
                "line": [{
                    "color": "0",
                    "content": "到監獄找醫生"
                }],
                "dot": []
            },
            "8":{
                "line": [{
                    "color": "0",
                    "content": "研發部會議"
                }],
                "dot": []
            },
            "15":{
                "line": [{
                    "color": "0",
                    "content": "研發部會議"
                }],
                "dot": []
            },
            "22":{
                "line": [{
                    "color": "0",
                    "content": "研發部會議"
                }],
                "dot": []
            }
        }
    }
}